jimaku_dl/__init__.py
jimaku_dl/cli.py
jimaku_dl/compat.py
jimaku_dl/downloader.py
jimaku_dl-0.1.40.1.4.dist-info/LICENSE
jimaku_dl-0.1.40.1.4.dist-info/METADATA
jimaku_dl-0.1.40.1.4.dist-info/WHEEL
jimaku_dl-0.1.40.1.4.dist-info/entry_points.txt
jimaku_dl-0.1.40.1.4.dist-info/top_level.txt
jimaku_dl-0.1.40.1.4.dist-info/RECORD
