Metadata-Version: 2.2
Name: jimaku-dl
Version: 0.1.40.1.4
Summary: Download japanese anime subtitles from Jimaku
Home-page: https://github.com/ksyasuda/jimaku-dl
Author: sudacode
Author-email: suda@sudacode.com
Project-URL: Bug Tracker, https://github.com/ksyasuda/jimaku-dl/issues
Classifier: Programming Language :: Python :: 3
Classifier: Programming Language :: Python :: 3.8
Classifier: Programming Language :: Python :: 3.9
Classifier: Programming Language :: Python :: 3.10
Classifier: Programming Language :: Python :: 3.11
Classifier: Programming Language :: Python :: 3.13
Classifier: License :: OSI Approved :: MIT License
Classifier: Operating System :: OS Independent
Classifier: Topic :: Multimedia :: Video
Classifier: Topic :: Utilities
Requires-Python: >=3.8
License-File: LICENSE
Requires-Dist: requests>=2.25.0
Requires-Dist: guessit>=3.4.0
